enelyzer_api_client/__init__.py
enelyzer_api_client/api/__init__.py
enelyzer_api_client/api/activities/__init__.py
enelyzer_api_client/api/activities/get_co2_emissions.py
enelyzer_api_client/api/activities/get_energy_consumption.py
enelyzer_api_client/api/assets/__init__.py
enelyzer_api_client/api/assets/search_facilities.py
enelyzer_api_client/api/audit_logging/__init__.py
enelyzer_api_client/api/audit_logging/filter_last_reporting_rendition_editor.py
enelyzer_api_client/api/audit_logging/get_last_reporting_rendition_editor.py
enelyzer_api_client/api/co2/__init__.py
enelyzer_api_client/api/co2/get_co2_calculation_methods.py
enelyzer_api_client/api/co2/get_co2_categories.py
enelyzer_api_client/api/co2/get_co2_scopes.py
enelyzer_api_client/api/get_facility_tags_by_notebook_labels/__init__.py
enelyzer_api_client/api/get_facility_tags_by_notebook_labels/get_labeled_tags_in_facility.py
enelyzer_api_client/api/notebooks/__init__.py
enelyzer_api_client/api/notebooks/delete_resource_file.py
enelyzer_api_client/api/notebooks/download_resource_file.py
enelyzer_api_client/api/notebooks/list_resource_files.py
enelyzer_api_client/api/notebooks/upload_resource_file.py
enelyzer_api_client/api/system_status/__init__.py
enelyzer_api_client/api/system_status/alive.py
enelyzer_api_client/api/system_status/openapi_json.py
enelyzer_api_client/api/tags/__init__.py
enelyzer_api_client/api/tags/add_reporting_rendition.py
enelyzer_api_client/api/tags/get_tag.py
enelyzer_api_client/api/tags/get_tags.py
enelyzer_api_client/api/tags/get_tags_by_ids.py
enelyzer_api_client/api/tags/query_tag.py
enelyzer_api_client/api/units_categories_and_quantities/__init__.py
enelyzer_api_client/api/units_categories_and_quantities/get_categories.py
enelyzer_api_client/api/units_categories_and_quantities/get_quantities.py
enelyzer_api_client/api/units_categories_and_quantities/get_units.py
enelyzer_api_client/auth.py
enelyzer_api_client/client.py
enelyzer_api_client/errors.py
enelyzer_api_client-0.4.3.dist-info/METADATA
enelyzer_api_client-0.4.3.dist-info/WHEEL
enelyzer_api_client-0.4.3.dist-info/licenses/LICENSE
enelyzer_api_client-0.4.3.dist-info/RECORD
